iwantadmin/__init__.py
iwantadmin/api_generator/__init__.py
iwantadmin/api_generator/model_api_generator.py
iwantadmin/api_generator/template_api_generator.py
iwantadmin/constants/__init__.py
iwantadmin/constants/const.py
iwantadmin/constants/errors.py
iwantadmin/managers/__init__.py
iwantadmin/managers/base.py
iwantadmin/templates/404.html
iwantadmin/templates/column_add.html
iwantadmin/templates/column_detail.html
iwantadmin/templates/index.html
iwantadmin/templates/include/pagination.html
iwantadmin/templates/layout/default.html
iwantadmin/utils/__init__.py
iwantadmin/utils/paginator.py
iwantadmin/utils/patch.py
iwantadmin/views/__init__.py
iwantadmin/views/base.py
iwantadmin/views/bulk_create_view.py
iwantadmin/views/column_add_view.py
iwantadmin/views/column_delete_view.py
iwantadmin/views/column_detail_view.py
iwantadmin/views/column_edit_view.py
iwantadmin/views/create_view.py
iwantadmin/views/delete_view.py
iwantadmin/views/filter_page_view.py
iwantadmin/views/filter_values_view.py
iwantadmin/views/filter_view.py
iwantadmin/views/get_view.py
iwantadmin/views/tables_view.py
iwantadmin/views/update_view.py
iwantadmin-0.0.7.dist-info/LICENSE
iwantadmin-0.0.7.dist-info/METADATA
iwantadmin-0.0.7.dist-info/WHEEL
iwantadmin-0.0.7.dist-info/top_level.txt
iwantadmin-0.0.7.dist-info/RECORD
